fastapi_request_id/__init__.py
fastapi_request_id/context.py
fastapi_request_id/handlers.py
fastapi_request_id/logging.py
fastapi_request_id/middleware.py
fastapi_request_id-1.1.2.dist-info/METADATA
fastapi_request_id-1.1.2.dist-info/WHEEL
fastapi_request_id-1.1.2.dist-info/RECORD
