Metadata-Version: 2.1
Name: fastapi-request-id
Version: 1.1.2
Summary: 
Author: Stanislav Tsoy
Author-email: dev.stanislav@gmail.com
Requires-Python: >=3.9,<4.0
Classifier: Programming Language :: Python :: 3
Classifier: Programming Language :: Python :: 3.9
Classifier: Programming Language :: Python :: 3.10
Classifier: Programming Language :: Python :: 3.11
Requires-Dist: fastapi (>=0.95.1,<0.96.0)
